{"version":1,"dimensions":2,"itemCount":18,"updatedAt":"2026-06-08T18:53:22.335Z","items":[{"id":"song:1","metadata":{"name":"Song A"},"embedding":[1,0]},{"id":"song:2","metadata":{"name":"Song B"},"embedding":[0,1]},{"id":"song:3","metadata":{"name":"Song C"},"embedding":[1,1]},{"id":"s2","metadata":{"name":"B","genre":"pop","year":"2023"},"embedding":[0.9,0.1]},{"id":"s1","metadata":{"name":"Original"},"embedding":[1]},{"id":"x","metadata":{"name":"X-axis"},"embedding":[1,0,0]},{"id":"y","metadata":{"name":"Y-axis"},"embedding":[0,1,0]},{"id":"z","metadata":{"name":"Z-axis"},"embedding":[0,0,1]},{"id":"s0","metadata":{"name":"Song 0"},"embedding":[0.25532671716134525,0.6987141680468799]},{"id":"s3","metadata":{"name":"C","genre":"rock","year":"2024"},"embedding":[0.8,0.2]},{"id":"s4","metadata":{"name":"Song 4"},"embedding":[0.9952857367544768,0.26597559460053255]},{"id":"s5","metadata":{"name":"Song 5"},"embedding":[0.9268985202444646,0.7355555394074718]},{"id":"s6","metadata":{"name":"Song 6"},"embedding":[0.6438934755615104,0.7384450014539746]},{"id":"s7","metadata":{"name":"Song 7"},"embedding":[0.23258473087872844,0.18363781716237115]},{"id":"s8","metadata":{"name":"Song 8"},"embedding":[0.12225437712246856,0.15840638837057475]},{"id":"s9","metadata":{"name":"Song 9"},"embedding":[0.4360912257742874,0.6510414935264265]},{"id":"exact","metadata":{"name":"Exact Match"},"embedding":[0.5,0.5,0.5,0.5]},{"id":"ortho","metadata":{"name":"Orthogonal"},"embedding":[1,0,0]}]}